Workbook

Sheet 使い方
B2: 職員の採用・退職に伴う届出 ヒアリングシート
B3: 作成日：2026-10-10 目的：届出担当者の事務負担軽減（スクリプト化の対象選定）
B5: ■ お願いしたいこと
B6: 「届出一覧」シートの黄色の列にご記入ください（分かる範囲で結構です）。
B7: 1. 現在の提出方法（プルダウン選択）
B8: 2. 年間件数（おおよそで可）
B9: 3. 1件あたりの作業時間（分。準備・転記・確認・提出までの合計）
B10: 4. 困っている点・手間がかかる点（自由記入）
B11: 5. 改善の優先度（高・中・低）
B12: ※ 緑色の「年間作業時間」は自動計算されます（Excelで開くと計算されます）。
B13: ※ 一覧に載っていない届出・作業があれば、表の下の空欄行に追記してください。
B14: ※ 対象外（当法人では発生しない）の届出は、提出方法で「該当なし」を選んでください。
... B26: ・期限等は2026年10月時点の一般的な内容です。最新の様式・期限は各提出先で確認してください。

Sheet 届出一覧
A1: 職員の採用・退職に伴う届出一覧（ヒアリング用）
A2: 黄色の列＝ご記入欄 ／ 緑色の列＝自動計算
A4: No | B4: 届出先 | C4: 場面 | D4: 届出名 | E4: 期限 | F4: 対象・備考 | G4: 現在の提出方法 | H4: 年間件数 | I4: 1件あたり作業時間（分） | J4: 年間作業時間（時間） | K4: 困っている点・手間がかかる点 | L4: 改善の優先度 | M4: スクリプト化判定（仮） | N4: 判定理由
A5: 1 | B5: 年金事務所・協会けんぽ | C5: 採用 | D5: 健康保険・厚生年金保険 被保険者資格取得届 | E5: 事実発生から5日以内 | F5: 全ての社保加入者 | G5: 紙（窓口・郵送） | I5: 15 | J5: =IF(AND(H5>0,I5>0),ROUND(H5*I5/60,1),"") | K5: 届出作成後、目視での確認のため記載漏れが発見しにくい。選択式または雇用保険資格取得届のように入力チェック機能があるとよい。 | M5: ◎ | N5: 年金機構「届書作成プログラム」用CSVの仕様が公開されている。台帳から自動作成し電子申請可能
A6: 2 | B6: 年金事務所・協会けんぽ | C6: 採用 | D6: 被扶養者（異動）届／国民年金第3号被保険者関係届 | E6: 事実発生から5日以内 | F6: 扶養家族がいる場合 | G6: 紙（窓口・郵送） | I6: 20 | J6: =IF(AND(H6>0,I6>0),ROUND(H6*I6/60,1),"") | M6: ○ | N6: 取得届と同じデータで作成可。続柄・収入等の確認は人が行う
A7: 3 | B7: 年金事務所・協会けんぽ | C7: 採用・退職 | D7: 70歳以上被用者 該当届／不該当届 | E7: 事実発生から5日以内 | F7: 70歳以上の職員 | G7: 紙（窓口・郵送） | J7: =IF(AND(H7>0,I7>0),ROUND(H7*I7/60,1),"") | M7: ○ | N7: 取得届・喪失届と同時に自動判定・作成できる
A8: 4 | B8: 年金事務所・協会けんぽ | C8: 退職 | D8: 健康保険・厚生年金保険 被保険者資格喪失届 | E8: 事実発生から5日以内 | F8: 全ての社保加入者 | G8: 紙（窓口・郵送） | I8: 15 | J8: =IF(AND(H8>0,I8>0),ROUND(H8*I8/60,1),"") | M8: ◎ | N8: 取得届と同様。退職日を入れるだけで作成可能
A9: 5 | B9: ハローワーク | C9: 採用 | D9: 雇用保険被保険者資格取得届 | E9: 翌月10日 | F9: 週20時間以上の職員 | G9: 紙（窓口・郵送） | I9: 15 | J9: =IF(AND(H9>0,I9>0),ROUND(H9*I9/60,1),"") | K9: ハローワークインターネットサービスで内容を入力して印刷できる（届出作成プログラム）。個人番号は印刷してから手書きにて記入。 | M9: ◎ | N9: 社保と共通データで作成可。届書作成プログラム／e-Govで提出
A10: 6 | B10: ハローワーク | C10: 退職 | D10: 雇用保険被保険者資格喪失届 | E10: 退職翌日から10日以内 | F10: 雇用保険加入者 | G10: 紙（窓口・郵送） | I10: 10 | J10: =IF(AND(H10>0,I10>0),ROUND(H10*I10/60,1),"") | M10: ◎ | N10: 取得届と同様
A11: 7 | B11: ハローワーク | C11: 退職 | D11: 雇用保険被保険者離職証明書 | E11: 喪失届と同時 | F11: 本人希望時／59歳以上は必須 | G11: 紙（窓口・郵送） | I11: 30 | J11: =IF(AND(H11>0,I11>0),ROUND(H11*I11/60,1),"") | K11: 手書きのみ | M11: ○ | N11: 直近12か月の賃金欄をMJS給与データから自動集計可。離職理由・最終確認は人
A12: 8 | B12: ハローワーク | C12: 採用・退職 | D12: 外国人雇用状況届出 | E12: 雇保加入者:取得・喪失届と同時／非加入者:翌月末日 | F12: 外国人職員（特別永住者除く） | G12: 紙（窓口・郵送） | J12: =IF(AND(H12>0,I12>0),ROUND(H12*I12/60,1),"") | M12: ○ | N12: 現在開発中のツールの対象。雇保届出と連動させると二度手間がなくなる
A13: 9 | B13: ハローワーク | C13: 退職 | D13: 障害者解雇届／多数離職届 | E13: 遅滞なく | F13: 障害者の解雇時／1か月30人以上の離職時 | J13: =IF(AND(H13>0,I13>0),ROUND(H13*I13/60,1),"") | M13: × | N13: 発生がまれ。チェックリストで漏れ防止のみ
A14: 10 | B14: 出入国在留管理局 | C14: 採用・退職 | D14: 特定技能雇用契約に係る届出（締結・変更・終了） | E14: 14日以内 | F14: 特定技能外国人 | J14: =IF(AND(H14>0,I14>0),ROUND(H14*I14/60,1),"") | M14: ○ | N14: 参考様式（Excel）への自動転記が可能。件数次第
A15: 11 | B15: 出入国在留管理局 | C15: 退職 | D15: 受入れ困難に係る届出／支援計画変更届 | E15: 14日以内 | F15: 特定技能外国人 | J15: =IF(AND(H15>0,I15>0),ROUND(H15*I15/60,1),"") | M15: △ | N15: 理由記載など判断を伴う部分が多い
A16: 12 | B16: 出入国在留管理局 | C16: 定期 | D16: 受入れ・活動状況に関する届出 | E16: 年1回（2025年4月～） | F16: 特定技能外国人 | J16: =IF(AND(H16>0,I16>0),ROUND(H16*I16/60,1),"") | M16: ○ | N16: 台帳から在籍者・報酬を集計して転記可能
A17: 13 | B17: 出入国在留管理局 | C17: 採用・退職 | D17: 中長期在留者の受入れに関する届出 | E17: 14日以内（努力義務） | F17: 技人国等。外国人雇用状況届出を出していれば不要 | J17: =IF(AND(H17>0,I17>0),ROUND(H17*I17/60,1),"") | M17: × | N17: 通常は外国人雇用状況届出で代替されるため対象外
A18: 14 | B18: 市町村（住民税） | C18: 採用 | D18: 特別徴収への切替届出（前職からの引継ぎ含む） | E18: 随時 | F18: 中途採用者で前職が特別徴収の場合等 | G18: 紙（窓口・郵送） | I18: 20 | J18: =IF(AND(H18>0,I18>0),ROUND(H18*I18/60,1),"") | K18: 市町村によって様式が異なる。（手書きのみの市町村も） | M18: ○ | N18: 住所地の市町村別に自動振分け作成可能
A19: 15 | B19: 市町村（住民税） | C19: 退職 | D19: 給与所得者異動届出書 | E19: 翌月10日 | F19: 特別徴収の職員 | G19: 紙（窓口・郵送） | I19: 20 | J19: =IF(AND(H19>0,I19>0),ROUND(H19*I19/60,1),"") | K19: 市町村によって様式が異なる。（手書きのみの市町村も） | M19: ○ | N19: 市町村別に自動作成可。eLTAX提出にも対応可能。780名規模では効果大
A20: 16 | B20: 福祉医療機構（WAM） | C20: 採用・退職 | D20: 社会福祉施設職員等退職手当共済 加入届／退職届 | E20: 共済規程で要確認 | F20: 共済対象職員 | J20: =IF(AND(H20>0,I20>0),ROUND(H20*I20/60,1),"") | M20: △ | N20: WAM NET電子届出（Web画面入力）のため、転記用一覧の作成支援が中心
A21: 17 | B21: 福祉医療機構（WAM） | C21: 退職 | D21: 退職手当金請求書 | E21: 退職後 | F21: 共済加入期間1年以上の退職者 | J21: =IF(AND(H21>0,I21>0),ROUND(H21*I21/60,1),"") | M21: △ | N21: 本人記入が主。法人証明欄の事前印字程度
A22: 18 | B22: 県社協・福利厚生団体 | C22: 採用・退職 | D22: 県民間退職共済／ソウェルクラブ等の加入・脱退届 | E22: 各団体の規程による | F22: 加入している場合のみ | J22: =IF(AND(H22>0,I22>0),ROUND(H22*I22/60,1),"") | M22: △ | N22: 様式次第。ヒアリングで加入状況を確認
A23: 19 | B23: 指定権者（県・市町村 介護保険／障害福祉） | C23: 採用・退職 | D23: 変更届（管理者・サビ管・サ責・介護支援専門員等の交代） | E23: 10日以内 | F23: 人員基準上の役職者 | J23: =IF(AND(H23>0,I23>0),ROUND(H23*I23/60,1),"") | M23: × | N23: 自治体ごとに様式が異なり件数も少ない。チェックリストで漏れ防止
A24: 20 | B24: 指定権者（県・市町村 介護保険／障害福祉） | C24: 採用・退職 | D24: 体制届（人員変動で加算要件が変わる場合） | E24: 算定月の前月15日等 | F24: 加算算定事業所 | J24: =IF(AND(H24>0,I24>0),ROUND(H24*I24/60,1),"") | M24: × | N24: 判断を伴う。チェックリストで漏れ防止
A25: 21 | B25: 本人交付・法人保管（参考） | C25: 採用 | D25: 扶養控除等申告書（保管） | E25: 初回給与支払まで | F25: 全職員 | J25: =IF(AND(H25>0,I25>0),ROUND(H25*I25/60,1),"") | M25: － | N25: 届出ではないが作業が発生
A26: 22 | B26: 本人交付・法人保管（参考） | C26: 退職 | D26: 給与所得の源泉徴収票（本人交付） | E26: 退職後1か月以内 | F26: 全退職者 | J26: =IF(AND(H26>0,I26>0),ROUND(H26*I26/60,1),"") | M26: ○ | N26: 給与システムから出力済みなら対象外
A27: 23 | B27: 本人交付・法人保管（参考） | C27: 退職 | D27: 退職所得の源泉徴収票／退職所得の受給に関する申告書 | E27: 退職後1か月以内 | F27: 退職金支給者 | J27: =IF(AND(H27>0,I27>0),ROUND(H27*I27/60,1),"") | M27: △ | N27: 給与システムの機能を確認
A28: 24 | B28: 本人交付・法人保管（参考） | C28: 退職 | D28: 退職証明書 | E28: 請求があれば遅滞なく | F28: 請求者 | J28: =IF(AND(H28>0,I28>0),ROUND(H28*I28/60,1),"") | M28: ○ | N28: 台帳から定型文書を自動作成可能
A29: 25 | B29: （横断） | C29: 採用・退職 | D29: 【新規】届出チェックリスト自動生成 | E29: － | F29: 入退職者全員 | J29: =IF(AND(H29>0,I29>0),ROUND(H29*I29/60,1),"") | M29: ◎ | N29: 入職/退職・国籍・扶養・役職を入れると必要な届出と期限を一覧化。最も簡単で漏れ防止効果大
D30: 合計 | H30: =SUM(H5:H29) -> 0 | J30: =SUM(J5:J29) -> 0

Sheet 届出先別集計
A1: 届出先別の集計（ヒアリング記入後に自動計算）
A3: 届出先 | B3: 届出数 | C3: 年間件数 計 | D3: 年間作業時間 計（時間） | E3: ◎・○ の届出数
A4: 年金事務所・協会けんぽ | B4: =COUNTIF(届出一覧!$B$5:$B$29,A4) -> 4 | C4: =SUMIF(届出一覧!$B$5:$B$29,A4,届出一覧!$H$5:$H$29) -> 0 | D4: =SUMIF(届出一覧!$B$5:$B$29,A4,届出一覧!$J$5:$J$29) -> 0 | E4: =COUNTIFS(届出一覧!$B$5:$B$29,A4,届出一覧!$M$5:$M$29,"◎")+COUNTIFS(届出一覧!$B$5:$B$29,A4,届出一覧!$M$5:$M$29,"○") -> 4
A5: ハローワーク | B5: =COUNTIF(届出一覧!$B$5:$B$29,A5) -> 5 | C5: =SUMIF(届出一覧!$B$5:$B$29,A5,届出一覧!$H$5:$H$29) -> 0 | D5: =SUMIF(届出一覧!$B$5:$B$29,A5,届出一覧!$J$5:$J$29) -> 0 | E5: =COUNTIFS(届出一覧!$B$5:$B$29,A5,届出一覧!$M$5:$M$29,"◎")+COUNTIFS(届出一覧!$B$5:$B$29,A5,届出一覧!$M$5:$M$29,"○") -> 4
A6: 出入国在留管理局 | B6: =COUNTIF(届出一覧!$B$5:$B$29,A6) -> 4 | C6: =SUMIF(届出一覧!$B$5:$B$29,A6,届出一覧!$H$5:$H$29) -> 0 | D6: =SUMIF(届出一覧!$B$5:$B$29,A6,届出一覧!$J$5:$J$29) -> 0 | E6: =COUNTIFS(届出一覧!$B$5:$B$29,A6,届出一覧!$M$5:$M$29,"◎")+COUNTIFS(届出一覧!$B$5:$B$29,A6,届出一覧!$M$5:$M$29,"○") -> 2
A7: 市町村（住民税） | B7: =COUNTIF(届出一覧!$B$5:$B$29,A7) -> 2 | C7: =SUMIF(届出一覧!$B$5:$B$29,A7,届出一覧!$H$5:$H$29) -> 0 | D7: =SUMIF(届出一覧!$B$5:$B$29,A7,届出一覧!$J$5:$J$29) -> 0 | E7: =COUNTIFS(届出一覧!$B$5:$B$29,A7,届出一覧!$M$5:$M$29,"◎")+COUNTIFS(届出一覧!$B$5:$B$29,A7,届出一覧!$M$5:$M$29,"○") -> 2
A8: 福祉医療機構（WAM） | B8: =COUNTIF(届出一覧!$B$5:$B$29,A8) -> 2 | C8: =SUMIF(届出一覧!$B$5:$B$29,A8,届出一覧!$H$5:$H$29) -> 0 | D8: =SUMIF(届出一覧!$B$5:$B$29,A8,届出一覧!$J$5:$J$29) -> 0 | E8: =COUNTIFS(届出一覧!$B$5:$B$29,A8,届出一覧!$M$5:$M$29,"◎")+COUNTIFS(届出一覧!$B$5:$B$29,A8,届出一覧!$M$5:$M$29,"○") -> 0
A9: 県社協・福利厚生団体 | B9: =COUNTIF(届出一覧!$B$5:$B$29,A9) -> 1 | C9: =SUMIF(届出一覧!$B$5:$B$29,A9,届出一覧!$H$5:$H$29) -> 0 | D9: =SUMIF(届出一覧!$B$5:$B$29,A9,届出一覧!$J$5:$J$29) -> 0 | E9: =COUNTIFS(届出一覧!$B$5:$B$29,A9,届出一覧!$M$5:$M$29,"◎")+COUNTIFS(届出一覧!$B$5:$B$29,A9,届出一覧!$M$5:$M$29,"○") -> 0
A10: 指定権者（県・市町村 介護保険／障害福祉） | B10: =COUNTIF(届出一覧!$B$5:$B$29,A10) -> 2 | C10: =SUMIF(届出一覧!$B$5:$B$29,A10,届出一覧!$H$5:$H$29) -> 0 | D10: =SUMIF(届出一覧!$B$5:$B$29,A10,届出一覧!$J$5:$J$29) -> 0 | E10: =COUNTIFS(届出一覧!$B$5:$B$29,A10,届出一覧!$M$5:$M$29,"◎")+COUNTIFS(届出一覧!$B$5:$B$29,A10,届出一覧!$M$5:$M$29,"○") -> 0
A11: 本人交付・法人保管（参考） | B11: =COUNTIF(届出一覧!$B$5:$B$29,A11) -> 4 | C11: =SUMIF(届出一覧!$B$5:$B$29,A11,届出一覧!$H$5:$H$29) -> 0 | D11: =SUMIF(届出一覧!$B$5:$B$29,A11,届出一覧!$J$5:$J$29) -> 0 | E11: =COUNTIFS(届出一覧!$B$5:$B$29,A11,届出一覧!$M$5:$M$29,"◎")+COUNTIFS(届出一覧!$B$5:$B$29,A11,届出一覧!$M$5:$M$29,"○") -> 2
A12: （横断） | B12: =COUNTIF(届出一覧!$B$5:$B$29,A12) -> 1 | C12: =SUMIF(届出一覧!$B$5:$B$29,A12,届出一覧!$H$5:$H$29) -> 0 | D12: =SUMIF(届出一覧!$B$5:$B$29,A12,届出一覧!$J$5:$J$29) -> 0 | E12: =COUNTIFS(届出一覧!$B$5:$B$29,A12,届出一覧!$M$5:$M$29,"◎")+COUNTIFS(届出一覧!$B$5:$B$29,A12,届出一覧!$M$5:$M$29,"○") -> 1
A13: 合計 | B13: =SUM(B4:B12) -> 25 | C13: =SUM(C4:C12) -> 0 | D13: =SUM(D4:D12) -> 0 | E13: =SUM(E4:E12) -> 15
